[
    {
        "across": "VL0",
        "across_source": false,
        "constant": "L0",
        "constant_type": "L",
        "in_normal": false,
        "source_node": 0,
        "target_node": 1,
        "through": "iL0",
        "through_source": false,
        "type": "T",
        "value": 9.875041334617737
    },
    {
        "across": "Vs",
        "across_source": true,
        "constant": "",
        "constant_type": "S",
        "in_normal": false,
        "source_node": 1,
        "target_node": 2,
        "through": "is",
        "through_source": false,
        "type": "S",
        "value": 1.624259815126508
    },
    {
        "across": "VC2",
        "across_source": false,
        "constant": "C2",
        "constant_type": "C",
        "in_normal": false,
        "source_node": 2,
        "target_node": 3,
        "through": "iC2",
        "through_source": false,
        "type": "A",
        "value": 3.432603935869322
    },
    {
        "across": "VL3",
        "across_source": false,
        "constant": "L3",
        "constant_type": "L",
        "in_normal": false,
        "source_node": 3,
        "target_node": 0,
        "through": "iL3",
        "through_source": false,
        "type": "T",
        "value": 7.962779648349176
    }
]